disws/__init__.py
disws/__main__.py
disws/base/__init__.py
disws/base/api_base.py
disws/base/client.py
disws/base/intents.py
disws/base/user.py
disws/base/websocket.py
disws/utils/__init__.py
disws/utils/converters.py
disws/utils/info_types.py
disws/utils/logger.py
disws/utils/utils.py
disws-0.0.3.dist-info/LICENSE
disws-0.0.3.dist-info/METADATA
disws-0.0.3.dist-info/WHEEL
disws-0.0.3.dist-info/RECORD
